quickstarter_mcp_server/__init__.py
quickstarter_mcp_server/detect_language_server.py
quickstarter_mcp_server/guidelines.py
quickstarter_mcp_server-0.1.1.dist-info/METADATA
quickstarter_mcp_server-0.1.1.dist-info/WHEEL
quickstarter_mcp_server-0.1.1.dist-info/entry_points.txt
quickstarter_mcp_server-0.1.1.dist-info/RECORD
