Metadata-Version: 2.4
Name: quickstarter-mcp-server
Version: 0.1.1
Summary: Add your description here
Author-email: Youjun Go <youjun.go@sk.com>
Requires-Python: >=3.12
Requires-Dist: build>=1.3.0
Requires-Dist: mcp>=1.12.3
Requires-Dist: twine>=6.1.0
